Workbook

Sheet Income statement
A1: CONSOLIDATED INCOME STATEMENT LVMH | H1: vertical analysis | M1: horizontal analysis
A3: in € millions | C3: 2024 | D3: 2023 | E3: 2022 | G3: % of revenue 2024 | H3: % of revenue 2023 | I3: % of revenue 2022 | K3: Δ 2024-2023 (€) | L3: Δ 2024–2023 (%) | N3: Δ 2023-2022 (€) | O3: Δ 2023–2022 (%)
B5: Revenue | C5: 84683 | D5: 86153 | E5: 79184 | G5: 1 | H5: 1 | I5: 1 | K5: =C5-D5 -> -1470 | L5: =(C5-D5)/D5 -> -0.017062668 | N5: =D5-E5 -> 6969 | O5: =(D5-E5)/E5 -> 0.088010204
B6: Cost of sales | C6: -27918 | D6: -26876 | E6: -24988 | G6: =(C6/C5) -> -0.32967656 | H6: =(D6/D5) -> -0.31195664 | I6: =(E6/E5) -> -0.3155688 | K6: =C6-D6 -> -1042 | L6: =(C6-D6)/D6 -> 0.03877065 | N6: =D6-E6 -> -1888 | O6: =(D6-E6)/E6 -> 0.075556267
A8: GROSS PROFIT | C8: 56765 | D8: 59277 | E8: 54196 | G8: =C8/C5 -> 0.67032344 | H8: =D8/D5 -> 0.68804336 | I8: =E8/E5 -> 0.6844312 | K8: =C8-D8 -> -2512 | L8: =(C8-D8)/D8 -> -0.042377313 | N8: =D8-E8 -> 5081 | O8: =(D8-E8)/E8 -> 0.093752306
B10: Marketing & selling expenses | C10: -31002 | D10: -30768 | E10: -28151 | G10: =(C10/$C$5) -> -0.36609473 | H10: =(D10/D5) -> -0.35713208 | I10: =(E10/E5) -> -0.35551374 | K10: =C10-D10 -> -234 | L10: =(C10-D10)/D10 -> 0.0076053042 | N10: =D10-E10 -> -2617 | O10: =(D10-E10)/E10 -> 0.09296295
B11: General and administrative expenses | C11: -6220 | D11: -5714 | E11: -5027 | G11: =(C11/$C$5) -> -0.073450397 | H11: =(D11/D5) -> -0.066323866 | I11: =(E11/E5) -> -0.063485047 | K11: =C11-D11 -> -506 | L11: =(C11-D11)/D11 -> 0.088554428 | N11: =D11-E11 -> -687 | O11: =(D11-E11)/E11 -> 0.13666203
B12: Income (Loss) from JVs and associates | C12: 28 | D12: 7 | E12: 37 | G12: =(C12/C5) -> 0.00033064488 | H12: =(D12/D5) -> 8.1250798e-05 | I12: =(E12/E5) -> 0.00046726611 | K12: =C12-D12 -> 21 | L12: =(C12-D12)/D12 -> 3 | N12: =D12-E12 -> -30 | O12: =(D12-E12)/E12 -> -0.81081081
A14: RECURRING OPERATING PROFIT | C14: 19571 | D14: 22802 | E14: 21055 | G14: =C14/C5 -> 0.23110896 | H14: =D14/D5 -> 0.26466867 | I14: =E14/E5 -> 0.26589968 | K14: =C14-D14 -> -3231 | L14: =(C14-D14)/D14 -> -0.1416981 | N14: =D14-E14 -> 1747 | O14: =(D14-E14)/E14 -> 0.082973166
B16: Other operating income less expenses | C16: -664 | D16: -242 | E16: -54 | G16: =(C16/C5) -> -0.007841007 | H16: =(D16/D5) -> -0.0028089562 | I16: =(E16/E5) -> -0.00068195595 | K16: =C16-D16 -> -422 | L16: =(C16-D16)/D16 -> 1.7438017 | N16: =D16-E16 -> -188 | O16: =(D16-E16)/E16 -> 3.4814815
A18: OPERATING PROFIT | C18: 18907 | D18: 22560 | E18: 21001 | G18: =C18/C5 -> 0.22326795 | H18: =D18/D5 -> 0.26185971 | I18: =E18/E5 -> 0.26521772 | K18: =C18-D18 -> -3653 | L18: =(C18-D18)/D18 -> -0.16192376 | N18: =D18-E18 -> 1559 | O18: =(D18-E18)/E18 -> 0.07423456
B20: Cost of net financial debt | C20: -442 | D20: -367 | E20: -17 | G20: =(C20/C5) -> -0.0052194655 | H20: =(D20/D5) -> -0.0042598633 | I20: =(E20/E5) -> -0.00021468984 | K20: =C20-D20 -> -75 | L20: =(C20-D20)/D20 -> 0.20435967 | N20: =D20-E20 -> -350 | O20: =(D20-E20)/E20 -> 20.588235
B21: Interest on lease liabilities | C21: -510 | D21: -393 | E21: -254 | G21: =(C21/C5) -> -0.0060224602 | H21: =(D21/D5) -> -0.0045616519 | I21: =(E21/E5) -> -0.0032077187 | K21: =C21-D21 -> -117 | L21: =(C21-D21)/D21 -> 0.29770992 | N21: =D21-E21 -> -139 | O21: =(D21-E21)/E21 -> 0.54724409
B22: Other financial income less expenses | C22: 160 | D22: -175 | E22: -617 | G22: =(C22/C5) -> 0.0018893993 | H22: =(D22/D5) -> -0.00203127 | I22: =(E22/E5) -> -0.0077919782 | K22: =C22-D22 -> 335 | L22: =(C22-D22)/D22 -> -1.9142857 | N22: =D22-E22 -> 442 | O22: =(D22-E22)/E22 -> -0.71636953
A24: PROFIT BEFORE TAX | C24: 18115 | D24: 21625 | E24: 20113 | G24: =C24/C5 -> 0.21391543 | H24: =D24/D5 -> 0.25100693 | I24: =E24/E5 -> 0.25400333 | K24: =C24-D24 -> -3510 | L24: =(C24-D24)/D24 -> -0.16231214 | N24: =D24-E24 -> 1512 | O24: =(D24-E24)/E24 -> 0.07517526
B26: Income taxes | C26: -5157 | D26: -5673 | E26: -5362 | F26: =C26/C24 -> -0.2846812 | G26: =(C26/C5) -> -0.060897701 | H26: =(D26/D5) -> -0.065847968 | I26: =(E26/E5) -> -0.0677157 | K26: =C26-D26 -> 516 | L26: =(C26-D26)/D26 -> -0.090957166 | N26: =D26-E26 -> -311 | O26: =(D26-E26)/E26 -> 0.058000746
A28: NET PROFIT | C28: 12958 | D28: 15952 | E28: 14751 | G28: =C28/C5 -> 0.15301772 | H28: =D28/D5 -> 0.18515896 | I28: =E28/E5 -> 0.18628763 | K28: =C28-D28 -> -2994 | L28: =(C28-D28)/D28 -> -0.18768806 | N28: =D28-E28 -> 1201 | O28: =(D28-E28)/E28 -> 0.081418209
A30: Of which:
B31: Profit attributable to minority interests | C31: 408 | D31: 778 | E31: 667 | G31: =C31/C5 -> 0.0048179682 | H31: =D31/D5 -> 0.0090304458 | I31: =E31/E5 -> 0.0084234189 | K31: =C31-D31 -> -370 | L31: =(C31-D31)/D31 -> -0.47557841 | N31: =D31-E31 -> 111 | O31: =(D31-E31)/E31 -> 0.16641679
B32: Profit attributable to LVMH shareholders (group part) | C32: 12550 | D32: 15174 | E32: 14084 | G32: =C32/C5 -> 0.14819976 | H32: =D32/D5 -> 0.17612852 | I32: =E32/E5 -> 0.17786421 | K32: =C32-D32 -> -2624 | L32: =(C32-D32)/D32 -> -0.17292738 | N32: =D32-E32 -> 1090 | O32: =(D32-E32)/E32 -> 0.077392786

Sheet Balance sheet
A1: CONSOLIDATED BALANCE SHEET LVMH | I1: vertical analysis | O1: horizontal analysis
A3: in € millions | C3: 2024 | D3: 2023 | E3: 2022 | H3: 2024 | I3: 2023 | J3: 2022 | M3: Δ 2024-2023 (€) | N3: Δ 2024–2023 (%) | P3: Δ 2023–2022 (€) | Q3: Δ 2023–2022 (%)
A5: NON-CURRENT ASSETS
B6: Brands and other intangible assets | C6: 26280 | D6: 25589 | E6: 25432 | H6: =C6/C20 -> 0.17615122 | I6: =D6/D20 -> 0.17807981 | J6: =E6/E20 -> 0.18888047 | M6: =C6-D6 -> 691 | N6: =(C6-D6)/D6 -> 0.027003791 | P6: =D6-E6 -> 157 | Q6: =(D6-E6)/E6 -> 0.0061733249
B7: Goodwill | C7: 20307 | D7: 24022 | E7: 24782 | H7: =C7/C20 -> 0.13611502 | I7: =D7/D20 -> 0.16717469 | J7: =E7/E20 -> 0.184053 | M7: =C7-D7 -> -3715 | N7: =(C7-D7)/D7 -> -0.1546499 | P7: =D7-E7 -> -760 | Q7: =(D7-E7)/E7 -> -0.03066742
B8: Property, Plant & Equipment | C8: 29886 | D8: 27331 | E8: 23055 | H8: =C8/C20 -> 0.20032174 | I8: =D8/D20 -> 0.19020279 | J8: =E8/E20 -> 0.17122677 | M8: =C8-D8 -> 2555 | N8: =(C8-D8)/D8 -> 0.09348359 | P8: =D8-E8 -> 4276 | Q8: =(D8-E8)/E8 -> 0.18546953
B9: Right-of-use assets | C9: 16620 | D9: 15679 | E9: 14615 | H9: =C9/C20 -> 0.11140157 | I9: =D9/D20 -> 0.10911381 | J9: =E9/E20 -> 0.10854389 | M9: =C9-D9 -> 941 | N9: =(C9-D9)/D9 -> 0.060016583 | P9: =D9-E9 -> 1064 | Q9: =(D9-E9)/E9 -> 0.072801916
B10: Other non-current assets | C10: =1343+1632+1106+4545 -> 8626 | D10: =991+1363+1017+3992 -> 7363 | E10: =1066+1109+1186+3661 -> 7022 | H10: =C10/C20 -> 0.057818889 | I10: =D10/D20 -> 0.051240831 | J10: =E10/E20 -> 0.052151568 | M10: =C10-D10 -> 1263 | N10: =(C10-D10)/D10 -> 0.17153334 | P10: =D10-E10 -> 341 | Q10: =(D10-E10)/E10 -> 0.048561663
B11: Total non-current assets | C11: =SUM(C6:C10) -> 101719 | D11: =SUM(D6:D10) -> 99984 | E11: =SUM(E6:E10) -> 94906 | H11: =C11/C20 -> 0.68180843 | I11: =D11/D20 -> 0.69581193 | J11: =E11/E20 -> 0.7048557 | M11: =C11-D11 -> 1735 | N11: =(C11-D11)/D11 -> 0.017352776 | P11: =D11-E11 -> 5078 | Q11: =(D11-E11)/E11 -> 0.053505574
A13: CURRENT ASSETS
B14: Inventories and WIP | C14: 23669 | D14: 22952 | E14: 20319 | H14: =C14/C20 -> 0.15865004 | I14: =D14/D20 -> 0.15972831 | J14: =E14/E20 -> 0.15090682 | M14: =C14-D14 -> 717 | N14: =(C14-D14)/D14 -> 0.031239108 | P14: =D14-E14 -> 2633 | Q14: =(D14-E14)/E14 -> 0.12958315
B15: Trade receivables | C15: 4730 | D15: 4728 | E15: 4258 | H15: =C15/C20 -> 0.031704538 | I15: =D15/D20 -> 0.032903253 | J15: =E15/E20 -> 0.031623665 | M15: =C15-D15 -> 2 | N15: =(C15-D15)/D15 -> 0.00042301184 | P15: =D15-E15 -> 470 | Q15: =(D15-E15)/E15 -> 0.11038046
B16: Other current assets | C16: =986+8455 -> 9441 | D16: =533+7723 -> 8256 | E16: =375+7488 -> 7863 | H16: =C16/C20 -> 0.063281721 | I16: =D16/D20 -> 0.057455426 | J16: =E16/E20 -> 0.058397576 | M16: =C16-D16 -> 1185 | N16: =(C16-D16)/D16 -> 0.14353198 | P16: =D16-E16 -> 393 | Q16: =(D16-E16)/E16 -> 0.049980923
B17: Cash & cash equivalents | C17: 9631 | D17: 7774 | E17: 7300 | H17: =C17/C20 -> 0.064555265 | I17: =D17/D20 -> 0.054101076 | J17: =E17/E20 -> 0.054216241 | M17: =C17-D17 -> 1857 | N17: =(C17-D17)/D17 -> 0.23887317 | P17: =D17-E17 -> 474 | Q17: =(D17-E17)/E17 -> 0.064931507
B18: Total current assets | C18: =SUM(C14:C17) -> 47471 | D18: =SUM(D14:D17) -> 43710 | E18: =SUM(E14:E17) -> 39740 | H18: =C18/C20 -> 0.31819157 | I18: =D18/D20 -> 0.30418807 | J18: =E18/E20 -> 0.2951443 | M18: =C18-D18 -> 3761 | N18: =(C18-D18)/D18 -> 0.086044383 | P18: =D18-E18 -> 3970 | Q18: =(D18-E18)/E18 -> 0.099899346
A20: TOTAL ASSETS | C20: =C11+C18 -> 149190 | D20: =D11+D18 -> 143694 | E20: =E11+E18 -> 134646 | H20: 1 | I20: 1 | J20: 1 | M20: =C20-D20 -> 5496 | N20: =(C20-D20)/D20 -> 0.038247944 | P20: =D20-E20 -> 9048 | Q20: =(D20-E20)/E20 -> 0.067198431
A23: in € millions | C23: 2024 | D23: 2023 | E23: 2022
A25: EQUITY
B26: Share capital (including additional paid-in capital) | C26: =150+53 -> 203 | D26: =151+530 -> 681 | E26: =151+1289 -> 1440 | H26: =C26/C48 -> 0.001360681 | I26: =D26/D48 -> 0.0047392375 | J26: =E26/E48 -> 0.010694711 | M26: =C26-D26 -> -478 | N26: =(C26-D26)/D26 -> -0.70190896 | P26: =D26-E26 -> -759 | Q26: =(D26-E26)/E26 -> -0.52708333
B27: Treasury shares | C27: -603 | D27: -1953 | E27: -1293 | H27: =C27/C48 -> -0.0040418259 | I27: =D27/D48 -> -0.013591382 | J27: =E27/E48 -> -0.0096029589 | M27: =C27-D27 -> 1350 | N27: =(C27-D27)/D27 -> -0.69124424 | P27: =D27-E27 -> -660 | Q27: =(D27-E27)/E27 -> 0.51044084
B28: CTA and revaluation reserves | C28: =2881-161+1173+218 -> 4111 | D28: =1525+66+1156+170-1 -> 2916 | E28: =2586+9+1125+151+1 -> 3872 | H28: =C28/C48 -> 0.027555466 | I28: =D28/D48 -> 0.020293123 | J28: =E28/E48 -> 0.028756888 | M28: =C28-D28 -> 1195 | N28: =(C28-D28)/D28 -> 0.40980796 | P28: =D28-E28 -> -956 | Q28: =(D28-E28)/E28 -> -0.24690083
B29: Retained earnings (excluding current year profit) | C29: =63806-12550 -> 51256 | D29: =59373-15174 -> 44199 | E29: =51092-14084 -> 37008 | H29: =C29/C48 -> 0.3435619 | I29: =D29/D48 -> 0.30759113 | J29: =E29/E48 -> 0.27485406 | M29: =C29-D29 -> 7057 | N29: =(C29-D29)/D29 -> 0.15966425 | P29: =D29-E29 -> 7191 | Q29: =(D29-E29)/E29 -> 0.19430934
B30: Net profit (group part) | C30: 12550 | D30: 15174 | E30: 14084 | H30: =C30/C48 -> 0.08412092 | I30: =D30/D48 -> 0.1055994 | J30: =E30/E48 -> 0.10460021 | M30: =C30-D30 -> -2624 | N30: =(C30-D30)/D30 -> -0.17292738 | P30: =D30-E30 -> 1090 | Q30: =(D30-E30)/E30 -> 0.077392786
B31: Minority interests | C31: 1770 | D31: 1684 | E31: 1493 | H31: =C31/C48 -> 0.011864066 | I31: =D31/D48 -> 0.011719348 | J31: =E31/E48 -> 0.011088335 | M31: =C31-D31 -> 86 | N31: =(C31-D31)/D31 -> 0.051068884 | P31: =D31-E31 -> 191 | Q31: =(D31-E31)/E31 -> 0.12793034
B32: Total equity | C32: =SUM(C26:C31) -> 69287 | D32: =SUM(D26:D31) -> 62701 | E32: =SUM(E26:E31) -> 56604 | H32: =C32/C48 -> 0.46442121 | I32: =D32/D48 -> 0.43635086 | J32: =E32/E48 -> 0.42039125 | M32: =C32-D32 -> 6586 | N32: =(C32-D32)/D32 -> 0.1050382 | P32: =D32-E32 -> 6097 | Q32: =(D32-E32)/E32 -> 0.10771324
A34: NON-CURRENT LIABILITIES
B35: Long-term borrowings | C35: 12091 | D35: 11227 | E35: 10380 | H35: =C35/C48 -> 0.081044306 | I35: =D35/D48 -> 0.078131307 | J35: =E35/E48 -> 0.077091039 | M35: =C35-D35 -> 864 | N35: =(C35-D35)/D35 -> 0.076957335 | P35: =D35-E35 -> 847 | Q35: =(D35-E35)/E35 -> 0.081599229
B36: Non-current lease liabilities | C36: 14860 | D36: 13810 | E36: 12776 | H36: =C36/C48 -> 0.099604531 | I36: =D36/D48 -> 0.096107005 | J36: =E36/E48 -> 0.094885849 | M36: =C36-D36 -> 1050 | N36: =(C36-D36)/D36 -> 0.076031861 | P36: =D36-E36 -> 1034 | Q36: =(D36-E36)/E36 -> 0.080932999
B37: Other non-current liabilities | C37: =3856+7344 -> 11200 | D37: =3880+7012 -> 10892 | E37: =3902+6952 -> 10854 | H37: =C37/C48 -> 0.075072056 | I37: =D37/D48 -> 0.075799964 | J37: =E37/E48 -> 0.080611381 | M37: =C37-D37 -> 308 | N37: =(C37-D37)/D37 -> 0.028277635 | P37: =D37-E37 -> 38 | Q37: =(D37-E37)/E37 -> 0.0035010135
B38: Purchase commitments for minority interests' shares | C38: 8056 | D38: 11919 | E38: 12489 | H38: =C38/C48 -> 0.053998257 | I38: =D38/D48 -> 0.082947096 | J38: =E38/E48 -> 0.092754334 | M38: =C38-D38 -> -3863 | N38: =(C38-D38)/D38 -> -0.32410437 | P38: =D38-E38 -> -570 | Q38: =(D38-E38)/E38 -> -0.045640163
B39: Total non-current liabilities | C39: =SUM(C35:C38) -> 46207 | D39: =SUM(D35:D38) -> 47848 | E39: =SUM(E35:E38) -> 46499 | H39: =C39/C48 -> 0.30971915 | I39: =D39/D48 -> 0.33298537 | J39: =E39/E48 -> 0.3453426 | M39: =C39-D39 -> -1641 | N39: =(C39-D39)/D39 -> -0.034296104 | P39: =D39-E39 -> 1349 | Q39: =(D39-E39)/E39 -> 0.029011377
A41: CURRENT LIABILITIES
B42: Short-term borrowings | C42: 10851 | D42: 10680 | E42: 9359 | H42: =C42/C48 -> 0.072732757 | I42: =D42/D48 -> 0.074324606 | J42: =E42/E48 -> 0.069508192 | M42: =C42-D42 -> 171 | N42: =(C42-D42)/D42 -> 0.016011236 | P42: =D42-E42 -> 1321 | Q42: =(D42-E42)/E42 -> 0.14114756
B43: Current lease liabilities | C43: 2972 | D43: 2728 | E43: 2632 | H43: =C43/C48 -> 0.019920906 | I43: =D43/D48 -> 0.018984787 | J43: =E43/E48 -> 0.019547554 | M43: =C43-D43 -> 244 | N43: =(C43-D43)/D43 -> 0.089442815 | P43: =D43-E43 -> 96 | Q43: =(D43-E43)/E43 -> 0.036474164
B44: Trade payables | C44: 8630 | D44: 9049 | E44: 8788 | H44: =C44/C48 -> 0.0578457 | I44: =D44/D48 -> 0.062974098 | J44: =E44/E48 -> 0.065267442 | M44: =C44-D44 -> -419 | N44: =(C44-D44)/D44 -> -0.046303459 | P44: =D44-E44 -> 261 | Q44: =(D44-E44)/E44 -> 0.02969959
B45: Other current liabilities | C45: =1231+10012 -> 11243 | D45: =1148+9540 -> 10688 | E45: =1211+9553 -> 10764 | H45: =C45/C48 -> 0.075360279 | I45: =D45/D48 -> 0.07438028 | J45: =E45/E48 -> 0.079942962 | M45: =C45-D45 -> 555 | N45: =(C45-D45)/D45 -> 0.051927395 | P45: =D45-E45 -> -76 | Q45: =(D45-E45)/E45 -> -0.0070605723
B46: Total current liabilities | C46: =SUM(C42:C45) -> 33696 | D46: =SUM(D42:D45) -> 33145 | E46: =SUM(E42:E45) -> 31543 | H46: =C46/C48 -> 0.22585964 | I46: =D46/D48 -> 0.23066377 | J46: =E46/E48 -> 0.23426615 | M46: =C46-D46 -> 551 | N46: =(C46-D46)/D46 -> 0.016623925 | P46: =D46-E46 -> 1602 | Q46: =(D46-E46)/E46 -> 0.050787813
A48: TOTAL EQUITY AND LIABILITIES | C48: =C39+C46+C32 -> 149190 | D48: =D39+D46+D32 -> 143694 | E48: =E39+E46+E32 -> 134646 | H48: 1 | I48: 1 | J48: 1 | M48: =C48-D48 -> 5496 | N48: =(C48-D48)/D48 -> 0.038247944 | P48: =D48-E48 -> 9048 | Q48: =(D48-E48)/E48 -> 0.067198431

Sheet Cash flow statement
A1: CONSOLIDATED STATEMENT OF CASH FLOWS LVMH
A3: in € millions | C3: 2024 | D3: 2023 | E3: 2022 | G3: SUM over 3 years
A5: CASH POSITION JANUARY 1st | C5: 7520 | D5: 7100 | E5: 7817
A7: OPERATING CASH FLOWS
B8: Operating profit | C8: 18907 | D8: 22560 | E8: 21001 | G8: =SUM(C8:E8) -> 62468
B9: Depreciation, Amortization and Provisions | C9: =4568+3228 -> 7796 | D9: =4146+3031 -> 7177 | E9: =3219+3007 -> 6226 | G9: =SUM(C9:E9) -> 21199
B10: Interest paid (net financial debt and leases) | C10: =-357-483 -> -840 | D10: =-457-356 -> -813 | E10: =-74-240 -> -314 | G10: =SUM(C10:E10) -> -1967
B11: Tax paid | C11: -5531 | D11: -5730 | E11: -5604 | G11: =SUM(C11:E11) -> -16865
B12: Other operating cash flows | C12: =29+488 -> 517 | D12: =42-259 -> -217 | E12: =26-483 -> -457 | G12: =SUM(C12:E12) -> -157
B13: Change in working capital requirements | C13: -1925 | D13: -4577 | E13: -3019 | G13: =SUM(C13:E13) -> -9521
B14: Total operating cash flows | C14: =SUM(C8:C13) -> 18924 | D14: =SUM(D8:D13) -> 18400 | E14: =SUM(E8:E13) -> 17833 | G14: =SUM(C14:E14) -> 55157
A16: INVESTING CASH FLOWS
B17: Operating investments | C17: -5531 | D17: -7478 | E17: -4969 | G17: =SUM(C17:E17) -> -17978
B18: Acquisitions (net of proceeds from sale) | C18: -438 | D18: -721 | E18: -809 | G18: =SUM(C18:E18) -> -1968
B19: Other | C19: =9-579 -> -570 | D19: =5-116 -> -111 | E19: =7-149 -> -142 | G19: =SUM(C19:E19) -> -823
B20: Total investing cash flows | C20: =SUM(C17:C19) -> -6539 | D20: =SUM(D17:D19) -> -8310 | E20: =SUM(E17:E19) -> -5920 | G20: =SUM(C20:E20) -> -20769
A22: FINANCING CASH FLOWS
B24: Dividends paid | C24: -7322 | D24: -7159 | E24: -6774 | G24: =SUM(C24:E24) -> -21255
B25: Net increase (decrease) of borrowings | C25: =3595-3676 -> -81 | D25: =5990-3968 -> 2022 | E25: =3774-3891 -> -117 | G25: =SUM(C25:E25) -> 1824
B26: Repayment of lease liabilities | C26: -2915 | D26: -2818 | E26: -2751 | G26: =SUM(C26:E26) -> -8484
B27: Other | C27: =-173-224-1 -> -398 | D27: =-17-1569+144 -> -1442 | E27: =-351-1604-1088 -> -3043 | G27: =SUM(C27:E27) -> -4883
B28: Total financing cash flows | C28: =SUM(C24:C27) -> -10716 | D28: =SUM(D24:D27) -> -9397 | E28: =SUM(E24:E27) -> -12685 | G28: =SUM(C28:E28) -> -32798
B30: Exchange rate effect and other | C30: 80 | D30: -273 | E30: 55 | G30: =SUM(C30:E30) -> -138
A32: TOTAL CASH FLOWS | C32: =C14+C20+C28+C30 -> 1749 | D32: =D14+D20+D28+D30 -> 420 | E32: =E14+E20+E28+E30 -> -717
A34: CASH POSITION DECEMBER 31st | C34: =C5+C32 -> 9269 | D34: =D5+D32 -> 7520 | E34: =E5+E32 -> 7100

Sheet Simplified balance sheet
A1: SIMPLIFIED BALANCE SHEET LVMH
A3: Use of funds (in €M) | F3: Sources of funds (in €M)
C4: 2024 | D4: 2023 | E4: 2022 | H4: =C4 -> 2024 | I4: =D4 -> 2023 | J4: =E4 -> 2022
A5: NON-CURRENT ASSETS | F5: EQUITY
B6: Brands and other intangible assets | C6: ='Balance sheet'!C6 -> 26280 | D6: ='Balance sheet'!D6 -> 25589 | E6: ='Balance sheet'!E6 -> 25432 | G6: Share capital (including additional paid-in capital) | H6: ='Balance sheet'!C26 -> 203 | I6: ='Balance sheet'!D26 -> 681 | J6: ='Balance sheet'!E26 -> 1440
B7: Goodwill | C7: ='Balance sheet'!C7 -> 20307 | D7: ='Balance sheet'!D7 -> 24022 | E7: ='Balance sheet'!E7 -> 24782 | G7: Treasury shares | H7: ='Balance sheet'!C27 -> -603 | I7: ='Balance sheet'!D27 -> -1953 | J7: ='Balance sheet'!E27 -> -1293
B8: Property, Plant & Equipment | C8: ='Balance sheet'!C8 -> 29886 | D8: ='Balance sheet'!D8 -> 27331 | E8: ='Balance sheet'!E8 -> 23055 | G8: CTA and revaluation reserves | H8: ='Balance sheet'!C28 -> 4111 | I8: ='Balance sheet'!D28 -> 2916 | J8: ='Balance sheet'!E28 -> 3872
B9: Right-of-use assets | C9: ='Balance sheet'!C9 -> 16620 | D9: ='Balance sheet'!D9 -> 15679 | E9: ='Balance sheet'!E9 -> 14615 | G9: Retained earnings (excluding current year profit) | H9: ='Balance sheet'!C29 -> 51256 | I9: ='Balance sheet'!D29 -> 44199 | J9: ='Balance sheet'!E29 -> 37008
B10: Other non-current assets | C10: ='Balance sheet'!C10 -> 8626 | D10: ='Balance sheet'!D10 -> 7363 | E10: ='Balance sheet'!E10 -> 7022 | G10: Net profit (group part) | H10: ='Balance sheet'!C30 -> 12550 | I10: ='Balance sheet'!D30 -> 15174 | J10: ='Balance sheet'!E30 -> 14084
B11: Total non-current assets | C11: =SUM(C6:C10) -> 101719 | D11: =SUM(D6:D10) -> 99984 | E11: =SUM(E6:E10) -> 94906 | G11: Minority interests | H11: ='Balance sheet'!C31 -> 1770 | I11: ='Balance sheet'!D31 -> 1684 | J11: ='Balance sheet'!E31 -> 1493
G12: Total equity | H12: =SUM(H6:H11) -> 69287 | I12: =SUM(I6:I11) -> 62701 | J12: =SUM(J6:J11) -> 56604
A13: WORKING CAPITAL REQUIREMENT
B14: Inventories and WIP | C14: ='Balance sheet'!C14 -> 23669 | D14: ='Balance sheet'!D14 -> 22952 | E14: ='Balance sheet'!E14 -> 20319 | F14: LIABILITIES
B15: Trade receivables | C15: ='Balance sheet'!C15 -> 4730 | D15: ='Balance sheet'!D15 -> 4728 | E15: ='Balance sheet'!E15 -> 4258 | G15: Long-term borrowings | H15: ='Balance sheet'!C35 -> 12091 | I15: ='Balance sheet'!D35 -> 11227 | J15: ='Balance sheet'!E35 -> 10380
B16: Other current assets | C16: ='Balance sheet'!C16 -> 9441 | D16: ='Balance sheet'!D16 -> 8256 | E16: ='Balance sheet'!E16 -> 7863 | G16: Non-current lease liabilities | H16: ='Balance sheet'!C36 -> 14860 | I16: ='Balance sheet'!D36 -> 13810 | J16: ='Balance sheet'!E36 -> 12776
B17: Trade payables | C17: =-'Balance sheet'!C44 -> -8630 | D17: =-'Balance sheet'!D44 -> -9049 | E17: =-'Balance sheet'!E44 -> -8788 | G17: Current lease liabilities | H17: ='Balance sheet'!C43 -> 2972 | I17: ='Balance sheet'!D43 -> 2728 | J17: ='Balance sheet'!E43 -> 2632
B18: Other current liabilities | C18: =-'Balance sheet'!C45 -> -11243 | D18: =-'Balance sheet'!D45 -> -10688 | E18: =-'Balance sheet'!E45 -> -10764 | G18: Other non-current liabilities | H18: ='Balance sheet'!C37 -> 11200 | I18: ='Balance sheet'!D37 -> 10892 | J18: ='Balance sheet'!E37 -> 10854
B19: Working capital requirement | C19: =SUM(C14:C18) -> 17967 | D19: =SUM(D14:D18) -> 16199 | E19: =SUM(E14:E18) -> 12888 | G19: Purchase commitments for minority interests' shares | H19: ='Balance sheet'!C38 -> 8056 | I19: ='Balance sheet'!D38 -> 11919 | J19: ='Balance sheet'!E38 -> 12489
G20: Total liabilities | H20: =SUM(H15:H19) -> 49179 | I20: =SUM(I15:I19) -> 50576 | J20: =SUM(J15:J19) -> 49131
A22: CASH & CASH EQUIVALENTS | C22: ='Balance sheet'!C17 -> 9631 | D22: ='Balance sheet'!D17 -> 7774 | E22: ='Balance sheet'!E17 -> 7300 | F22: SHORT-TERM BORROWINGS | H22: ='Balance sheet'!C42 -> 10851 | I22: ='Balance sheet'!D42 -> 10680 | J22: ='Balance sheet'!E42 -> 9359
A24: Total use of funds | C24: =SUM(C22+C19+C11) -> 129317 | D24: =SUM(D22+D19+D11) -> 123957 | E24: =SUM(E22+E19+E11) -> 115094 | F24: Total sources of funds | H24: =H22+H20+H12 -> 129317 | I24: =I22+I20+I12 -> 123957 | J24: =J22+J20+J12 -> 115094

Sheet Ratios
A1: RATIOS and KPIs | B1: LVMH | E1: LVMH | H1: KERING | K1: RICHEMONT
B2: (your calculation) | E2: (Capital IQ) | H2: (Capital IQ) | K2: (Capital IQ)
A3: 1/ Growth: | B3: 2024 | C3: 2023 | E3: =+B3 -> 2024 | F3: =+C3 -> 2023 | H3: =$B$3 -> 2024 | I3: =$C$3 -> 2023 | K3: =$B$3 -> 2024 | L3: =$C$3 -> 2023
A5: Sales revenue growth | B5: =('Income statement'!C5/'Income statement'!D5)-1 -> -0.017062668 | C5: =('Income statement'!D5/'Income statement'!E5)-1 -> 0.088010204 | E5: =91615/93173-1 -> -0.016721582 | F5: =93173/83421-1 -> 0.11690102 | H5: =18601/21160-1 -> -0.12093573 | I5: =21160/21440-1 -> -0.013059701 | K5: =22361/20782-1 -> 0.075979213 | L5: =20782/19469-1 -> 0.067440547
A8: 2/ Profitability: | E8: =$B$3 -> 2024 | F8: =$C$3 -> 2023 | H8: =$B$3 -> 2024 | I8: =$C$3 -> 2023 | K8: =$B$3 -> 2024 | L8: =$C$3 -> 2023
A10: Gross margin | B10: =('Income statement'!C8/'Income statement'!C5) -> 0.67032344 | C10: =('Income statement'!D8/'Income statement'!D5) -> 0.68804336 | E10: 0.6703 | F10: 0.688 | H10: 0.7375 | I10: 0.7629 | K10: 0.6807 | L10: 0.6874
A12: EBITDA in M€ | B12: 26703 | C12: 29737
A14: EBITDA margin | B14: =B12/'Income statement'!C5 -> 0.31532893 | C14: =C12/'Income statement'!D5 -> 0.345165 | E14: 0.2649 | F14: 0.2932 | H14: 0.2047 | I14: 0.2863 | K14: 0.2659 | L14: 0.2874
A16: Operating margin | B16: =('Income statement'!C18/'Income statement'!C5) -> 0.22326795 | C16: =('Income statement'!D18/'Income statement'!D5) -> 0.26185971 | E16: 0.2312 | F16: 0.2644 | H16: 0.1485 | I16: 0.2426 | K16: 0.2358 | L16: 0.255
A18: Net margin | B18: =('Income statement'!C28/'Income statement'!C5) -> 0.15301772 | C18: =('Income statement'!D28/'Income statement'!D5) -> 0.18515896 | E18: 0.1482 | F18: 0.1761 | H18: 0.0659 | I18: 0.1525 | K18: 0.1146 | L18: 0.0157
A21: 3/ Cash generation: | E21: =$B$3 -> 2024 | F21: =$C$3 -> 2023 | H21: =$B$3 -> 2024 | I21: =$C$3 -> 2023 | K21: =$B$3 -> 2024 | L21: =$C$3 -> 2023
A23: Self-financing capacity in M€ | B23: ='Income statement'!C28+'Cash flow statement'!C9 -> 20754 | C23: ='Income statement'!D28+'Cash flow statement'!D9 -> 23129
A25: Self-financing capacity as a % of revenue | B25: =B23/'Income statement'!C5 -> 0.24507871 | C25: =C23/'Income statement'!D5 -> 0.26846424
A27: Free cash flows in M€ | B27: ='Cash flow statement'!C14+'Cash flow statement'!C17 -> 13393 | C27: ='Cash flow statement'!D14+'Cash flow statement'!D17 -> 10922
A29: Free cash flows as a % of revenue | B29: =B27/'Income statement'!C5 -> 0.15815453 | C29: =C27/'Income statement'!D5 -> 0.12677446 | E29: =12320/91615 -> 0.1344758 | F29: =9108/93173 -> 0.097753641 | H29: =696/18601 -> 0.037417343 | I29: =1357/21160 -> 0.064130435 | K29: =3038/22361 -> 0.13586154 | L29: =1771/20782 -> 0.085217977
A32: 4/ Return: | E32: =$B$3 -> 2024 | F32: =$C$3 -> 2023 | H32: =$B$3 -> 2024 | I32: =$C$3 -> 2023 | K32: =$B$3 -> 2024 | L32: =$C$3 -> 2023
A34: Return on Equity (ROE) | B34: =('Income statement'!C32/((('Balance sheet'!C32-'Balance sheet'!C31)+('Balance sheet'!D32-'Balance sheet'!D31))/2)) -> 0.19527907 | C34: =('Income statement'!D32/((('Balance sheet'!D32-'Balance sheet'!D31)+('Balance sheet'!E32-'Balance sheet'!E31))/2)) -> 0.26133232 | E34: 0.1964 | F34: 0.2674 | H34: 0.0773 | I34: 0.1997 | K34: 0.1926 | L34: 0.2012
A36: Assets turnover | B36: =('Income statement'!C5/(( 'Balance sheet'!C20 + 'Balance sheet'!D20)/2)) -> 0.5782699 | C36: =('Income statement'!D5/(( 'Balance sheet'!D20 + 'Balance sheet'!E20)/2)) -> 0.61904865
A38: Return on Capital Employed (ROCE) | B38: ='Income statement'!C18/('Balance sheet'!C20-'Balance sheet'!C46) -> 0.16370547 | C38: ='Income statement'!D18/('Balance sheet'!D20-'Balance sheet'!D46) -> 0.2040724 | E38: 0.1153 | F38: 0.1468 | H38: 0.0458 | I38: 0.0981 | K38: 0.0847 | L38: 0.0913
A42: 5/ Capital structure: | E42: =$B$3 -> 2024 | F42: =$C$3 -> 2023 | H42: =$B$3 -> 2024 | I42: =$C$3 -> 2023 | K42: =$B$3 -> 2024 | L42: =$C$3 -> 2023
A44: Net debt in M€ | B44: ='Balance sheet'!C35+'Balance sheet'!C42-'Balance sheet'!C17 -> 13311 | C44: ='Balance sheet'!D35+'Balance sheet'!D42-'Balance sheet'!D17 -> 14133
A46: Net debt to equity | B46: =B44/('Balance sheet'!C32-'Balance sheet'!C31) -> 0.19715035 | C46: =C44/('Balance sheet'!D32-'Balance sheet'!D31) -> 0.23162397 | E46: =28673/71733 -> 0.3997184 | F46: =30628/69306 -> 0.44192422 | H46: =17211/16285 -> 1.0568621 | I46: =15363/17696 -> 0.8681623 | K46: NA | L46: NA
A48: Total debt in M€ | B48: =('Balance sheet'!C35+'Balance sheet'!C42) -> 22942 | C48: =('Balance sheet'!D35+'Balance sheet'!D42) -> 21907
A50: Total debt to equity | B50: =B48/('Balance sheet'!C32-'Balance sheet'!C31) -> 0.3397959 | C50: =('Balance sheet'!D35+'Balance sheet'!D42)/(('Balance sheet'!D32-'Balance sheet'!D31)) -> 0.35903109 | E50: 0.5961 | F50: 0.622 | H50: 1.2805 | I50: 1.1131 | K50: 0.7931 | L50: 0.8262
A52: Debt horizon | B52: =B48/'Income statement'!C18 -> 1.213413 | C52: =C48/'Income statement'!D18 -> 0.97105496 | E52: 1.61 | F52: 1.38 | H52: 4.33 | I52: 2.71 | K52: 2.62 | L52: 2.43
A54: Interest coverage | B54: ='Income statement'!C18/ABS('Cash flow statement'!C10) -> 22.508333 | C54: ='Income statement'!D18/ABS('Cash flow statement'!D10) -> 27.749077 | E54: 16.51 | F54: 23.41 | H54: 4.24 | I54: 13.15 | K54: 10.95 | L54: 16.79
A57: 6/ Liquidity: | E57: =$B$3 -> 2024 | F57: =$C$3 -> 2023 | H57: =$B$3 -> 2024 | I57: =$C$3 -> 2023 | K57: =$B$3 -> 2024 | L57: =$C$3 -> 2023
A59: Current ratio | B59: ='Balance sheet'!C18/'Balance sheet'!C46 -> 1.4088022 | C59: ='Balance sheet'!D18/'Balance sheet'!D46 -> 1.3187509 | E59: 1.41 | F59: 1.32 | H59: 1.11 | I59: 1.38 | K59: 2.65 | L59: 2.47
A61: Acid test (also called Quick ratio) | B61: =('Balance sheet'!C18-'Balance sheet'!C14)/'Balance sheet'!C46 -> 0.70637464 | C61: =('Balance sheet'!D18-'Balance sheet'!D14)/'Balance sheet'!D46 -> 0.62627847 | E61: 0.66 | F61: 0.58 | H61: 0.54 | I61: 0.68 | K61: 1.8 | L61: 1.61
A63: Net cash in M€ | B63: ='Balance sheet'!C17-B48 -> -13311 | C63: ='Balance sheet'!D17-C48 -> -14133
A66: 7/ Working capital management: | E66: =$B$3 -> 2024 | F66: =$C$3 -> 2023 | H66: =$B$3 -> 2024 | I66: =$C$3 -> 2023 | K66: =$B$3 -> 2024 | L66: =$C$3 -> 2023
A68: DSO (Trade receivable in days of sales) | B68: =('Balance sheet'!C15/'Income statement'!C5)*365 -> 20.387209 | C68: =('Balance sheet'!D15/'Income statement'!D5)*365 -> 20.030875 | E68: 20.4 | F68: 19 | H68: 22.9 | I68: 21.7 | K68: 15.8 | L68: 14.5
A70: DIO (Inventory in days of Cost of sales) | B70: =('Balance sheet'!C14/ABS('Income statement'!C6))*365 -> 309.44856 | C70: =('Balance sheet'!D14/ABS('Income statement'!D6))*365 -> 311.70859 | E70: 305.6 | F70: 293.8 | H70: 346.4 | I70: 354.7 | K70: 419.2 | L70: 415.4
A72: LVMH operates in 6 different business sectors: wines and spirits, fashion and leather goods, perfumes and cosmetics, watches and jewelry, selective retailing and other (luxury yachts, luxury hotels, media).
A74: Kering operates in 4 different business sectors: fashion and leather goods, perfumes and cosmetics, watches and jewelry and other (eyewear).
A76: Compagnie financière Richemont operates in 3 different business sectors: fashion and leather goods, watches and jewelry and other (apparel and footwear, writing instruments, guns and rifles).
